Keys/__init__.py
Keys/main.py
Keys/statics/key.png
Keys/statics/keys.json
keys_manager-1.1.6.dist-info/LICENSE
keys_manager-1.1.6.dist-info/METADATA
keys_manager-1.1.6.dist-info/WHEEL
keys_manager-1.1.6.dist-info/entry_points.txt
keys_manager-1.1.6.dist-info/top_level.txt
keys_manager-1.1.6.dist-info/RECORD
