Metadata-Version: 2.1
Name: keys-manager
Version: 1.1.6
Summary: A simple key manager
Home-page: https://github.com/xiaochuan-li/keys
Author: Xiaochuan Li
Author-email: lixiaochuan822@gmail.com
License: UNKNOWN
Platform: UNKNOWN
License-File: LICENSE
Requires-Dist: PyQt5 (==5.15.4)
Requires-Dist: keyboard (==0.13.5)
Requires-Dist: PyAutoGUI (==0.9.50)
